MANIFEST.in
README.rst
setup.cfg
setup.py
django_dynamic_mailer.egg-info/PKG-INFO
django_dynamic_mailer.egg-info/SOURCES.txt
django_dynamic_mailer.egg-info/dependency_links.txt
django_dynamic_mailer.egg-info/requires.txt
django_dynamic_mailer.egg-info/top_level.txt
emails/__init__.py
emails/admin.py
emails/apps.py
emails/backends.py
emails/models.py
emails/serializers.py
emails/signals.py
emails/task.py
emails/tests.py
emails/urls.py
emails/views.py
emails/migrations/0001_initial.py
emails/migrations/__init__.py
emails/templates/email.html
emails/tests/__init__.py
emails/tests/factories.py
emails/tests/test_model.py
emails/tests/test_serializers.py
emails/tests/test_tasks.py
emails/tests/test_views.py
emails/tests/validation.py